Workbook

Sheet README
A1: RADIANT-MVT™ TRADING MODULE | DEVELOPMENT BACKLOG
A2: Source: AI Trading Intelligence Blueprint for INEOS (Caliche Energy Solutions, May 2026)
A4: PURPOSE
A5: This workbook translates the INEOS Trading AI deck into a prioritized engineering backlog the Caliche dev team
A6: can execute against. 45 epics across 5 architecture layers and 5 delivery phases. Built to map directly to the
A7: deck's 5-layer AI Orchestration framework and the 90-day pilot path with INEOS Trading & Shipping.
A9: HOW TO USE
A10: • BACKLOG tab — Full prioritized epic list — filter, sort, assign owners, paste into Jira. Each row is one epic.
A11: • PHASES tab — Phase-by-phase rollup showing what ships when, with the day-range and a summary deliverable.
A12: • BY LAYER tab — Architecture-layer rollup — Layer 1 through Layer 5 + cross-cutting platform work.
A13: • DASHBOARD tab — Live counts by priority, phase, layer, workstream. Auto-updates as Status column changes.
A15: CONVENTIONS
... A23: AT A GLANCE
A24: • Total epics | B24: =45 -> 45
A25: • P0 (critical) | B25: =COUNTIF(BACKLOG!B:B,"P0") -> 12
A26: • P1 (high) | B26: =COUNTIF(BACKLOG!B:B,"P1") -> 14
A27: • P2 (medium) | B27: =COUNTIF(BACKLOG!B:B,"P2") -> 12
A28: • P3 (low) | B28: =COUNTIF(BACKLOG!B:B,"P3") -> 7
A29: • Phase 1 (days 1-30) | B29: =COUNTIF(BACKLOG!C:C,"1 - Foundation") -> 9
A30: • Phase 2 (days 31-60) | B30: =COUNTIF(BACKLOG!C:C,"2 - Pilot") -> 7
A31: • Phase 3 (days 61-90) | B31: =COUNTIF(BACKLOG!C:C,"3 - Scale") -> 10
A32: • Phase 4 (days 91-180) | B32: =COUNTIF(BACKLOG!C:C,"4 - Harden") -> 12
A33: • Phase 5 (180+) | B33: =COUNTIF(BACKLOG!C:C,"5 - Expansion") -> 7
A36: CALICHE ENERGY SOLUTIONS · RADIANT-MVT™ TRADING MODULE · www.calichesolutions.com

Sheet BACKLOG
A1: RADIANT-MVT™ TRADING MODULE · BACKLOG
A3: ID | B3: Priority | C3: Phase | D3: Layer | E3: Workstream | F3: Epic | G3: Description | H3: Acceptance Criteria | I3: Effort | J3: Dependencies | K3: Status | L3: Owner | M3: Notes
A4: RMVT-T-001 | B4: P0 | C4: 1 - Foundation | D4: X - Cross-Cutting | E4: Platform/Infra | F4: Trading-Module API Gateway | G4: Stand up the trading-module API surface: auth, rate limiting, tenant routing, request/response logging. All trading-module services consumed via this gateway. | H4: OAuth2 + service-account auth working; per-tenant rate limits enforced; 99.95% uptime in load test; OpenAPI spec published. | I4: L | J4: — | K4: Backlog
A5: RMVT-T-002 | B5: P0 | C5: 1 - Foundation | D5: X - Cross-Cutting | E5: Platform/Infra | F5: Multi-Tenant Data Isolation for Trading Workspaces | G5: Trading data is highly sensitive. Build hard tenant boundaries (row-level + storage-level) so one trading-floor's data is never queryable by another. | H5: Per-tenant encryption keys; row-level security tested by red-team; audit log of every cross-boundary attempt. | I5: L | J5: RMVT-T-001 | K5: Backlog
A6: RMVT-T-003 | B6: P0 | C6: 1 - Foundation | D6: X - Cross-Cutting | E6: Platform/Infra | F6: TagTrack™ Extension for Trading Instruments | G6: Extend molecular tagging from physical commodities to financial instruments: every paper trade, futures contract, swap, and option receives an immutable Radiant-MVT ID linked to its physical-equivalent molecules. | H6: Every trade booked in pilot has a TagTrack ID; ID survives amendments/novations; chain-of-custody trace from physical lift to paper hedge passes audit. | I6: XL | J6: RMVT-T-002 | K6: Backlog
A7: RMVT-T-004 | B7: P0 | C7: 1 - Foundation | D7: X - Cross-Cutting | E7: Platform/Infra | F7: Audit Trail & Lineage Framework | G7: Immutable, append-only audit log for every read/write/calc on trading data. Required for Dodd-Frank, EMIR, REMIT compliance. | H7: Every position change traceable to its origin tick; auditor can replay any P&L number from raw inputs; tamper-evident hashes verified. | I7: L | J7: RMVT-T-002 | K7: Backlog
A8: RMVT-T-005 | B8: P0 | C8: 1 - Foundation | D8: L1 - Data Collection | E8: Connectors | F8: RightAngle Position & Trade Connector | G8: Real-time pull of positions, trades, amendments, and physical schedules from ION RightAngle. Leverage Caliche's founding-era RightAngle knowledge. | H8: Live trade feed <2s latency; handles novations/amendments idempotently; reconciles to RightAngle's own EOD reports at 99.5%+. | I8: L | J8: RMVT-T-003 | K8: Backlog
A9: RMVT-T-006 | B9: P0 | C9: 1 - Foundation | D9: L1 - Data Collection | E9: Connectors | F9: Platts & Argus Market Data Connector | G9: Pricing curves, indices, settlements from Platts and Argus. Includes historical backfill and intraday updates. | H9: All commodity curves used by pilot book ingested; intraday refresh on settlement events; 10-year historical backfill complete. | I9: M | J9: RMVT-T-001 | K9: Backlog
A10: RMVT-T-007 | B10: P0 | C10: 1 - Foundation | D10: L2 - Data Lake | E10: Data Platform | F10: Time-Series Store for Curves, Vols & Settlements | G10: Purpose-built TSDB for trading market data — fast slice by tenor, basis, region, commodity, vol point. | H10: 1B+ data points indexed; sub-100ms range queries; supports versioned curves (rebuilt vs. original). | I10: L | J10: RMVT-T-001 | K10: Backlog
A11: RMVT-T-008 | B11: P0 | C11: 1 - Foundation | D11: L2 - Data Lake | E11: Data Platform | F11: Trade Blotter Store with Full Lineage | G11: Every trade — booking, amendment, novation, termination — stored as an immutable event log with state-rebuild capability. | H11: Any historical position state reconstructible from event log; amendments traceable to user, system, timestamp; complete trade lifecycle queryable. | I11: L | J11: RMVT-T-003 | K11: Backlog
A12: RMVT-T-009 | B12: P0 | C12: 1 - Foundation | D12: L2 - Data Lake | E12: Data Platform | F12: Position History Store with Molecule Indexing | G12: Position snapshots keyed by TagTrack ID — every physical, paper, and exchange position queryable down to the molecule. | H12: Position-by-molecule queries return <500ms; reconciles to ETRM EOD; integrates with TagTrack lineage. | I12: L | J12: RMVT-T-003, RMVT-T-008 | K12: Backlog
A13: RMVT-T-010 | B13: P0 | C13: 2 - Pilot | D13: L3 - Analytics Engine | E13: Analytics | F13: Real-Time P&L Engine (Pilot Book) | G13: Intraday MTM and P&L attribution for the pilot commodity book — by trader, lane, molecule, strategy. | H13: P&L refresh <5s on market data tick; attribution sums to total; matches T+1 settlement P&L within tolerance. | I13: L | J13: RMVT-T-007, RMVT-T-009 | K13: Backlog
A14: RMVT-T-011 | B14: P0 | C14: 2 - Pilot | D14: L3 - Analytics Engine | E14: Analytics | F14: Position Aggregation Service | G14: Consolidate physical + paper + exchange positions into a single net view per commodity, region, tenor. | H14: Net position matches sum of constituents; handles cross-commodity offsets; updates within 5s of trade booking. | I14: M | J14: RMVT-T-005, RMVT-T-009 | K14: Backlog
A15: RMVT-T-012 | B15: P0 | C15: 2 - Pilot | D15: X - Cross-Cutting | E15: Data Platform | F15: Physical-to-Financial Reconciliation Engine | G15: Real-time reconciliation between physical operations data (lifts, transfers, inventory) and financial system positions — the core trust layer. | H15: 98.5%+ auto-match rate; exceptions surfaced with root-cause hints; replaces the T+1 spreadsheet reconciliation process. | I15: XL | J15: RMVT-T-009, RMVT-T-011 | K15: Backlog
... A48: RMVT-T-045 | B48: P3 | C48: 5 - Expansion | D48: L4 - AI/ML Models | E48: ML Models | F48: GenAI Trade Copilot v2 — Agentic Workflows | G48: Move from Q&A to action — copilot proposes trade tickets, runs scenarios, drafts confirmations under human approval. | H48: Trader can approve/reject proposed action; full audit log of agentic actions; rate limits to prevent runaway behavior. | I48: XL | J48: RMVT-T-026, RMVT-T-042 | K48: Backlog

Sheet PHASES
A1: PHASED ROADMAP · 90-DAY PILOT + BEYOND
A3: Phase | B3: Window | C3: Epics | D3: Build Focus | E3: Outcome at Phase End
A4: 1 - Foundation | B4: Days 1–30 | C4: =COUNTIF(BACKLOG!C:C,"1 - Foundation") -> 9 | D4: Stand up trading-module API, multi-tenancy, TagTrack for instruments, lineage framework. Connect RightAngle + first market data. Build trade blotter + position store. | E4: Sandbox alive with reconciled pilot-book data flowing end-to-end. No models yet.
A5: 2 - Pilot | B5: Days 31–60 | C5: =COUNTIF(BACKLOG!C:C,"2 - Pilot") -> 7 | D5: Real-time P&L and position aggregation for pilot book. Physical-to-financial reconciliation engine. First AI model — optimal hedging — in trader-in-the-loop production. Trader Desk Dashboard v1. | E5: Working AI model live for one trader. Baseline P&L and risk metrics captured.
A6: 3 - Scale | B6: Days 61–90 | C6: =COUNTIF(BACKLOG!C:C,"3 - Scale") -> 10 | D6: Add Endur/Allegro/exchange connectors. VaR + curve construction. Anomaly detection model. Middle Office dashboard. Contract corpus + GenAI Copilot v1. | E6: Pilot book operationalized. Second book onboarded on same foundation. CoE blueprint defined.
A7: 4 - Harden | B7: Days 91–180 | C7: =COUNTIF(BACKLOG!C:C,"4 - Harden") -> 12 | D7: Monte Carlo VaR, Greeks, settlement engine, regulatory reporting. Forecasting + trade idea models. Counterparty master. News/AIS feeds. Event-impact scoring. C-suite briefing. Alert routing. | E7: Production-grade across front, middle, and back office. Reg reporting live. Multiple AI models in production.
A8: 5 - Expansion | B8: 180+ days | C8: =COUNTIF(BACKLOG!C:C,"5 - Expansion") -> 7 | D8: Voice/chat capture + transcript vectorization. Trader annotation UI. MLOps platform. Reg/ESG dashboards. Credit signal feeds. Agentic GenAI Copilot. | E8: Standing AI Center of Excellence. Continuous model lifecycle. Trading floor operates with AI as embedded muscle.

Sheet BY LAYER
A1: ARCHITECTURE LAYER ROLLUP
A3: Layer | B3: Epics | C3: Purpose | D3: Capability Set
A4: L1 - Data Collection | B4: =COUNTIF(BACKLOG!D:D,"L1 - Data Collection") -> 10 | C4: Capture every signal that moves the trade — market data, ETRM, vessels, counterparties, news. | D4: • RightAngle / Endur / Allegro position feeds • Platts / Argus / Bloomberg market data • ICE / NYMEX FIX exchange connectors • AIS vessel tracking • News & sentiment feeds • Counterparty / credit signal feeds • Voice & chat capture
A5: L2 - Data Lake | B5: =COUNTIF(BACKLOG!D:D,"L2 - Data Lake") -> 6 | C5: Structured + unstructured trading data unified — the memory that compounds the desk's edge. | D5: • Time-series store for curves, vols, settlements • Trade blotter with full amendment lineage • Position history with molecule indexing • Counterparty master data • Contract corpus + vectorization (RAG) • Voice/chat transcripts vectorized
A6: L3 - Analytics Engine | B6: =COUNTIF(BACKLOG!D:D,"L3 - Analytics Engine") -> 8 | C6: Radiant-MVT Core for trading — where reconciled data becomes the truth layer for front, middle, back office. | D6: • Real-time P&L engine • Position aggregation service • VaR (parametric / historical / Monte Carlo) • Greeks calculator • Curve construction service • Settlement engine • Regulatory reporting (Dodd-Frank, EMIR, REMIT)
A7: L4 - AI/ML Models | B7: =COUNTIF(BACKLOG!D:D,"L4 - AI/ML Models") -> 9 | C7: Intelligence at trader speed — six model families on Radiant-MVT-grade data, all explainable, all trader-in-loop. | D7: • Optimal hedging recommendation • Anomaly detection / surveillance • GenAI Trade Copilot (RAG → agentic) • Forecasting (curves, basis, vol) • Trade idea generation • Event & sentiment impact scoring • Model lineage + MLOps
A8: L5 - Business Intelligence | B8: =COUNTIF(BACKLOG!D:D,"L5 - Business Intelligence") -> 6 | C8: Decisions at the speed of the market — audience-specific lenses on the same reconciled core. | D8: • Trader Desk Dashboard • Pre-trade margin & credit check • Middle Office & Risk Dashboard • C-Suite GenAI Briefing • Regulatory & ESG Reporting • Trader Annotation Capture
A9: X - Cross-Cutting | B9: =COUNTIF(BACKLOG!D:D,"X - Cross-Cutting") -> 6 | C9: Foundational platform capabilities every layer depends on. | D9: • Trading-module API gateway • Multi-tenant data isolation • TagTrack™ extension for instruments • Audit & lineage framework • Physical-to-financial reconciliation engine • Alert routing & escalation

Sheet DASHBOARD
A1: BACKLOG DASHBOARD · COUNTS BY DIMENSION
A3: BY PRIORITY | D3: BY PHASE | G3: BY LAYER
A4: P0 — critical | B4: =COUNTIF(BACKLOG!B:B,"P0") -> 12 | D4: 1 - Foundation | E4: =COUNTIF(BACKLOG!C:C,"1 - Foundation") -> 9 | G4: L1 - Data Collection | H4: =COUNTIF(BACKLOG!D:D,"L1 - Data Collection") -> 10
A5: P1 — high | B5: =COUNTIF(BACKLOG!B:B,"P1") -> 14 | D5: 2 - Pilot | E5: =COUNTIF(BACKLOG!C:C,"2 - Pilot") -> 7 | G5: L2 - Data Lake | H5: =COUNTIF(BACKLOG!D:D,"L2 - Data Lake") -> 6
A6: P2 — medium | B6: =COUNTIF(BACKLOG!B:B,"P2") -> 12 | D6: 3 - Scale | E6: =COUNTIF(BACKLOG!C:C,"3 - Scale") -> 10 | G6: L3 - Analytics Engine | H6: =COUNTIF(BACKLOG!D:D,"L3 - Analytics Engine") -> 8
A7: P3 — low | B7: =COUNTIF(BACKLOG!B:B,"P3") -> 7 | D7: 4 - Harden | E7: =COUNTIF(BACKLOG!C:C,"4 - Harden") -> 12 | G7: L4 - AI/ML Models | H7: =COUNTIF(BACKLOG!D:D,"L4 - AI/ML Models") -> 9
A8: Total | B8: =COUNTA(BACKLOG!A4:A100) -> 45 | D8: 5 - Expansion | E8: =COUNTIF(BACKLOG!C:C,"5 - Expansion") -> 7 | G8: L5 - BI | H8: =COUNTIF(BACKLOG!D:D,"L5 - Business Intelligence") -> 6
G9: X - Cross-Cutting | H9: =COUNTIF(BACKLOG!D:D,"X - Cross-Cutting") -> 6
A11: BY EFFORT | D11: BY WORKSTREAM | G11: BY STATUS
A12: S — ~1 week | B12: =COUNTIF(BACKLOG!I:I,"S") -> 0 | D12: Connectors | E12: =COUNTIF(BACKLOG!E:E,"Connectors") -> 10 | G12: Backlog | H12: =COUNTIF(BACKLOG!K:K,"Backlog") -> 45
A13: M — 2-4 weeks | B13: =COUNTIF(BACKLOG!I:I,"M") -> 16 | D13: Data Platform | E13: =COUNTIF(BACKLOG!E:E,"Data Platform") -> 7 | G13: In Progress | H13: =COUNTIF(BACKLOG!K:K,"In Progress") -> 0
A14: L — 1-2 months | B14: =COUNTIF(BACKLOG!I:I,"L") -> 26 | D14: Analytics | E14: =COUNTIF(BACKLOG!E:E,"Analytics") -> 8 | G14: In Review | H14: =COUNTIF(BACKLOG!K:K,"In Review") -> 0
A15: XL — 2-3 months | B15: =COUNTIF(BACKLOG!I:I,"XL") -> 3 | D15: ML Models | E15: =COUNTIF(BACKLOG!E:E,"ML Models") -> 9 | G15: Done | H15: =COUNTIF(BACKLOG!K:K,"Done") -> 0
D16: UX | E16: =COUNTIF(BACKLOG!E:E,"UX") -> 6 | G16: Blocked | H16: =COUNTIF(BACKLOG!K:K,"Blocked") -> 0
D17: Platform/Infra | E17: =COUNTIF(BACKLOG!E:E,"Platform/Infra") -> 5 | G17: % Complete | H17: =ROUND(COUNTIF(BACKLOG!K:K,"Done")/COUNTA(BACKLOG!A4:A100)*100,0) & "%" -> 0%
A20: CRITICAL PATH · P0 epics in Phase 1 (must ship before pilot)
A21: RMVT-T-001 | B21: Trading-Module API Gateway | F21: L | G21: —
A22: RMVT-T-002 | B22: Multi-Tenant Data Isolation for Trading Workspaces | F22: L | G22: RMVT-T-001
A23: RMVT-T-003 | B23: TagTrack™ Extension for Trading Instruments | F23: XL | G23: RMVT-T-002
A24: RMVT-T-004 | B24: Audit Trail & Lineage Framework | F24: L | G24: RMVT-T-002
A25: RMVT-T-005 | B25: RightAngle Position & Trade Connector | F25: L | G25: RMVT-T-003
A26: RMVT-T-006 | B26: Platts & Argus Market Data Connector | F26: M | G26: RMVT-T-001
A27: RMVT-T-007 | B27: Time-Series Store for Curves, Vols & Settlements | F27: L | G27: RMVT-T-001
A28: RMVT-T-008 | B28: Trade Blotter Store with Full Lineage | F28: L | G28: RMVT-T-003
A29: RMVT-T-009 | B29: Position History Store with Molecule Indexing | F29: L | G29: RMVT-T-003, RMVT-T-008
